hendrics/__init__.py
hendrics/_astropy_init.py
hendrics/_version.py
hendrics/base.py
hendrics/binary.py
hendrics/calibrate.py
hendrics/colors.py
hendrics/conftest.py
hendrics/create_gti.py
hendrics/efsearch.py
hendrics/exposure.py
hendrics/exvar.py
hendrics/fake.py
hendrics/ffa.py
hendrics/fold.py
hendrics/fspec.py
hendrics/io.py
hendrics/lcurve.py
hendrics/ml_timing.py
hendrics/modeling.py
hendrics/phaseogram.py
hendrics/phasetag.py
hendrics/plot.py
hendrics/power_colors.py
hendrics/read_events.py
hendrics/rebin.py
hendrics/save_as_xspec.py
hendrics/setup_package.py
hendrics/sum_fspec.py
hendrics/timelags.py
hendrics/varenergy.py
hendrics/version.py
hendrics/compat/__init__.py
hendrics/compat/compatibility.py
hendrics/compat/datasets/xselect.mdb
hendrics/licenses/LICENSE.rst
hendrics/licenses/README.rst
hendrics/tests/__init__.py
hendrics/tests/test_a_complete_run.py
hendrics/tests/test_base.py
hendrics/tests/test_binary.py
hendrics/tests/test_calibrate.py
hendrics/tests/test_colors.py
hendrics/tests/test_efsearch.py
hendrics/tests/test_exposure.py
hendrics/tests/test_fake.py
hendrics/tests/test_ffa.py
hendrics/tests/test_fspec.py
hendrics/tests/test_gti.py
hendrics/tests/test_io.py
hendrics/tests/test_lc.py
hendrics/tests/test_ml_timing.py
hendrics/tests/test_phaseogram.py
hendrics/tests/test_phasetag.py
hendrics/tests/test_read_events.py
hendrics/tests/data/lcurveA.fits
hendrics/tests/data/monol_testA.evt
hendrics/tests/data/monol_testA.pdf
hendrics/tests/data/monol_testA_mjdref.evt
hendrics/tests/data/monol_testA_nomission.evt
hendrics/tests/data/monol_testA_phasetag.evt
hendrics/tests/data/monol_testA_phasetag_phasetag.evt
hendrics/tests/data/monol_testA_timezero.evt
hendrics/tests/data/monol_testA_timezero_gti.evt
hendrics/tests/data/monol_testA_uf.evt
hendrics/tests/data/monol_testB.evt
hendrics/tests/data/test.rmf
hendrics/tests/data/xte_gx_test.evt
hendrics/tests/data/xte_gx_test.evt.gz
hendrics/tests/data/xte_test.evt.gz
hendrics-8.1.dist-info/LICENSE.rst
hendrics-8.1.dist-info/METADATA
hendrics-8.1.dist-info/WHEEL
hendrics-8.1.dist-info/entry_points.txt
hendrics-8.1.dist-info/top_level.txt
hendrics-8.1.dist-info/RECORD
