Metadata-Version: 2.1
Name: hendrics
Version: 8.1
Summary: High ENergy Data Reduction Interface from the Command Shell
Author-email: Matteo Bachetti <matteo@matteobachetti.it>
License: 3-clause BSD
Project-URL: homepage, https://stingray.science
Project-URL: documentation, https://hendrics.stingray.science
Project-URL: repository, https://github.com/stingraysoftware/hendrics
Keywords: astronomy,astrophysics,time series,X-ray,data analysis,black holes,neutron stars,pulsars,space,science
Classifier: Intended Audience :: Science/Research
Classifier: License :: OSI Approved :: BSD License
Classifier: Operating System :: OS Independent
Classifier: Programming Language :: C
Classifier: Programming Language :: Cython
Classifier: Programming Language :: Python :: 3
Classifier: Programming Language :: Python :: Implementation :: CPython
Classifier: Topic :: Scientific/Engineering :: Astronomy
Classifier: Topic :: Scientific/Engineering :: Physics
Requires-Python: >=3.9
License-File: LICENSE.rst
Requires-Dist: numpy (>=1.17)
Requires-Dist: astropy (>=4.0)
Requires-Dist: scipy (>=1.1.0)
Requires-Dist: matplotlib (!=3.4.00,!=3.8.0,>=3.0)
Requires-Dist: stingray (>=2.2.3)
Requires-Dist: tqdm
Requires-Dist: pyyaml
Provides-Extra: all
Requires-Dist: hendrics[recommended] ; extra == 'all'
Requires-Dist: pandas ; extra == 'all'
Requires-Dist: pint-pulsar ; extra == 'all'
Requires-Dist: imageio ; extra == 'all'
Requires-Dist: netcdf4 (==1.7.0) ; extra == 'all'
Requires-Dist: scikit-image ; extra == 'all'
Requires-Dist: statsmodels ; extra == 'all'
Provides-Extra: docs
Requires-Dist: jinja2 (==3.1.3) ; extra == 'docs'
Requires-Dist: docutils ; extra == 'docs'
Requires-Dist: sphinx-astropy ; extra == 'docs'
Requires-Dist: sphinx-toolbox ; extra == 'docs'
Requires-Dist: nbsphinx (!=0.8.8,>=0.8.3) ; extra == 'docs'
Requires-Dist: nbconvert (<7.14) ; extra == 'docs'
Requires-Dist: pandoc ; extra == 'docs'
Requires-Dist: ipython ; extra == 'docs'
Requires-Dist: towncrier (<22.12.0) ; extra == 'docs'
Requires-Dist: tomli (>=1.1.0) ; (python_version < "3.11") and extra == 'docs'
Provides-Extra: recommended
Requires-Dist: numba ; extra == 'recommended'
Requires-Dist: h5py ; extra == 'recommended'
Requires-Dist: pyyaml ; extra == 'recommended'
Requires-Dist: statsmodels ; extra == 'recommended'
Requires-Dist: pyfftw ; extra == 'recommended'
Provides-Extra: test
Requires-Dist: pytest ; extra == 'test'
Requires-Dist: pytest-astropy ; extra == 'test'
Provides-Extra: test_all
Requires-Dist: h5py ; extra == 'test_all'
Requires-Dist: pandas ; extra == 'test_all'
Requires-Dist: pint-pulsar ; extra == 'test_all'
Requires-Dist: imageio ; extra == 'test_all'
Requires-Dist: numba ; extra == 'test_all'
Requires-Dist: netcdf4 (==1.7.0) ; extra == 'test_all'
Requires-Dist: scikit-image ; extra == 'test_all'
Requires-Dist: statsmodels ; extra == 'test_all'
